sqlfluff_schema/__init__.py
sqlfluff_schema/core.py
sqlfluff_schema/ddl/C001_column_add_constant_default.py
sqlfluff_schema/ddl/C002_column_add_volatile_default.py
sqlfluff_schema/ddl/C003_column_add_constraint.py
sqlfluff_schema/ddl/C004_column_add_with_constraint.py
sqlfluff_schema/ddl/C005_column_alter_not_null.py
sqlfluff_schema/ddl/C006_column_alter_type.py
sqlfluff_schema/ddl/C007_column_drop.py
sqlfluff_schema/ddl/C008_column_key_type.py
sqlfluff_schema/ddl/C009_column_rename.py
sqlfluff_schema/ddl/N001_index_create.py
sqlfluff_schema/ddl/T001_table_alter_important.py
sqlfluff_schema/ddl/T002_table_drop.py
sqlfluff_schema/ddl/T003_table_move.py
sqlfluff_schema/ddl/T004_table_multiple_single_txn.py
sqlfluff_schema/ddl/T005_table_rename.py
sqlfluff_schema/ddl/__init__.py
sqlfluff_schema/default_config.cfg
sqlfluff_schema/dialect.py
sqlfluff_schema/grammar.py
sqlfluff_schema/rules.py
sqlfluff_schema/selectors.py
sqlfluff_schema/utils.py
sqlfluff_plugin_schema-0.0.1.dist-info/entry_points.txt
sqlfluff_plugin_schema-0.0.1.dist-info/WHEEL
sqlfluff_plugin_schema-0.0.1.dist-info/METADATA
sqlfluff_plugin_schema-0.0.1.dist-info/licenses/LICENSE
sqlfluff_plugin_schema-0.0.1.dist-info/RECORD
